{
  "zacatekTydne": {
    "den": 29,
    "mesic": 9,
    "rok": 2025
  },
  "Pondeli": {
    "jidla": [
      {
        "nazev": "Polévka – kapustová se slaninou a bramborem"
      },
      {
        "nazev": "Čočka na kyselo",
        "popis": "opečená klobása, okurek, cibulka, chléb",
        "cena": 185
      },
      {
        "nazev": "Vepřové kostky na hřibech se smetanou",
        "popis": "jasmínová rýže",
        "cena": 185
      },
      {
        "nazev": "Smažená gouda",
        "popis": "hranolky, domácí tatarka",
        "cena": 185
      }
    ]
  },
  "Utery": {
    "jidla": [
      {
        "nazev": "Polévka – kuřecí vývar s masem a zeleninou, tarhoňa"
      },
      {
        "nazev": "Chilli con carne",
        "popis": "zakysaná smetana s pažitkou, opečená tortilla",
        "cena": 185
      },
      {
        "nazev": "Vepřová kotleta na grilu",
        "popis": "pepřová omáčka, šťouchané brambory",
        "cena": 185
      },
      {
        "nazev": "Smažená gouda",
        "popis": "hranolky, domácí tatarka",
        "cena": 185
      },
      {
        "nazev": "Hovězí svíčková na smetaně",
        "popis": "houskový knedlík, brusinkový terč",
        "cena": 235
      }
    ]
  },
  "Streda": {
    "jidla": [
      {
        "nazev": "Polévka – květákový krém a římským kmínem"
      },
      {
        "nazev": "Špagety po milánsku",
        "popis": "sypané sýrem",
        "cena": 185
      },
      {
        "nazev": "Uzené maso",
        "popis": "křenová omáčka, houskový knedlík",
        "cena": 185
      },
      {
        "nazev": "Smažená gouda",
        "popis": "hranolky, domácí tatarka",
        "cena": 185
      },
      {
        "nazev": "Hovězí svíčková na smetaně",
        "popis": "houskový knedlík, brusinkový terč",
        "cena": 235
      }
    ]
  },
  "Ctvrtek": {
    "jidla": [
      {
        "nazev": "Polévka – hrášková"
      },
      {
        "nazev": "Pečená vepřová plec",
        "popis": "smetanový špenát, noky",
        "cena": 185
      },
      {
        "nazev": "Kuřecí závitek",
        "popis": "se šunkou a hermelínem, vařené brambory",
        "cena": 185
      },
      {
        "nazev": "Smažená gouda",
        "popis": "hranolky, domácí tatarka",
        "cena": 185
      },
      {
        "nazev": "Hovězí svíčková na smetaně",
        "popis": "houskový knedlík, brusinkový terč",
        "cena": 235
      }
    ]
  },
  "Patek": {
    "jidla": [
      {
        "nazev": "Polévka – kulajda"
      },
      {
        "nazev": "Ovocné kynuté knedlíky",
        "popis": "tvaroh, skořice, máslo",
        "cena": 185
      },
      {
        "nazev": "Obrácený vepřový řízek",
        "popis": "vídeňský bramborový salát",
        "cena": 185
      },
      {
        "nazev": "Smažená gouda",
        "popis": "hranolky, domácí tatarka",
        "cena": 185
      },
      {
        "nazev": "Hovězí svíčková na smetaně",
        "popis": "houskový knedlík, brusinkový terč",
        "cena": 235
      }
    ]
  }
}